{
  "_format": "hh-sol-cache-2",
  "files": {
    "/mnt/user-data/joe/aztec-connect-bridges/src/aztec/AztecTypes.sol": {
      "lastModificationDate": 1644078770742,
      "contentHash": "89c5c817c0fbf2444915b03ce4a4ddb5",
      "sourceName": "src/aztec/AztecTypes.sol",
      "solcConfig": {
        "version": "0.8.10",
        "settings": {
          "optimizer": {
            "enabled": false,
            "runs": 200
          },
          "outputSelection": {
            "*": {
              "*": [
                "abi",
                "evm.bytecode",
                "evm.deployedBytecode",
                "evm.methodIdentifiers",
                "metadata"
              ],
              "": [
                "ast"
              ]
            }
          }
        }
      },
      "imports": [],
      "versionPragmas": [
        ">=0.6.10 <=0.8.10"
      ],
      "artifacts": [
        "AztecTypes"
      ]
    },
    "/mnt/user-data/joe/aztec-connect-bridges/src/test/example/Example.t.sol": {
      "lastModificationDate": 1644321382026,
      "contentHash": "75036aaa6f1874a102d380a9f9242252",
      "sourceName": "src/test/example/Example.t.sol",
      "solcConfig": {
        "version": "0.8.10",
        "settings": {
          "optimizer": {
            "enabled": false,
            "runs": 200
          },
          "outputSelection": {
            "*": {
              "*": [
                "abi",
                "evm.bytecode",
                "evm.deployedBytecode",
                "evm.methodIdentifiers",
                "metadata"
              ],
              "": [
                "ast"
              ]
            }
          }
        }
      },
      "imports": [
        "../Vm.sol",
        "./../../aztec/DefiBridgeProxy.sol",
        "./../../aztec/RollupProcessor.sol",
        "@openzeppelin/contracts/token/ERC20/IERC20.sol",
        "./../../bridges/example/ExampleBridge.sol",
        "./../../aztec/AztecTypes.sol",
        "../../../lib/ds-test/src/test.sol"
      ],
      "versionPragmas": [
        "0.8.10"
      ],
      "artifacts": [
        "ExampleTest"
      ]
    },
    "/mnt/user-data/joe/aztec-connect-bridges/src/test/Vm.sol": {
      "lastModificationDate": 1644078770742,
      "contentHash": "39aab9a5820503a5ccc726832fbb7465",
      "sourceName": "src/test/Vm.sol",
      "solcConfig": {
        "version": "0.8.10",
        "settings": {
          "optimizer": {
            "enabled": false,
            "runs": 200
          },
          "outputSelection": {
            "*": {
              "*": [
                "abi",
                "evm.bytecode",
                "evm.deployedBytecode",
                "evm.methodIdentifiers",
                "metadata"
              ],
              "": [
                "ast"
              ]
            }
          }
        }
      },
      "imports": [],
      "versionPragmas": [
        "^0.8.0"
      ],
      "artifacts": [
        "Vm"
      ]
    },
    "/mnt/user-data/joe/aztec-connect-bridges/src/aztec/DefiBridgeProxy.sol": {
      "lastModificationDate": 1644331419329,
      "contentHash": "6ea3b228ca5ec1f1d45e17575b26b678",
      "sourceName": "src/aztec/DefiBridgeProxy.sol",
      "solcConfig": {
        "version": "0.8.10",
        "settings": {
          "optimizer": {
            "enabled": false,
            "runs": 200
          },
          "outputSelection": {
            "*": {
              "*": [
                "abi",
                "evm.bytecode",
                "evm.deployedBytecode",
                "evm.methodIdentifiers",
                "metadata"
              ],
              "": [
                "ast"
              ]
            }
          }
        }
      },
      "imports": [
        "@openzeppelin/contracts/utils/math/SafeMath.sol",
        "../interfaces/IDefiBridge.sol",
        "./AztecTypes.sol",
        "../libraries/TokenTransfers.sol",
        "../../lib/ds-test/src/test.sol"
      ],
      "versionPragmas": [
        ">=0.8.4 <0.8.11"
      ],
      "artifacts": [
        "DefiBridgeProxy"
      ]
    },
    "/mnt/user-data/joe/aztec-connect-bridges/src/aztec/RollupProcessor.sol": {
      "lastModificationDate": 1644332336579,
      "contentHash": "5bb630b9dc0c2b299fc24614da5d8be4",
      "sourceName": "src/aztec/RollupProcessor.sol",
      "solcConfig": {
        "version": "0.8.10",
        "settings": {
          "optimizer": {
            "enabled": false,
            "runs": 200
          },
          "outputSelection": {
            "*": {
              "*": [
                "abi",
                "evm.bytecode",
                "evm.deployedBytecode",
                "evm.methodIdentifiers",
                "metadata"
              ],
              "": [
                "ast"
              ]
            }
          }
        }
      },
      "imports": [
        "@openzeppelin/contracts/utils/math/SafeMath.sol",
        "../interfaces/IDefiBridge.sol",
        "../interfaces/IERC20Permit.sol",
        "./DefiBridgeProxy.sol",
        "./AztecTypes.sol",
        "../../lib/ds-test/src/test.sol"
      ],
      "versionPragmas": [
        ">=0.8.0 <=0.8.10"
      ],
      "artifacts": [
        "RollupProcessor"
      ]
    },
    "/mnt/user-data/joe/aztec-connect-bridges/node_modules/@openzeppelin/contracts/token/ERC20/IERC20.sol": {
      "lastModificationDate": 1644078429920,
      "contentHash": "302d9755e46bc69d7058b0cbe7185e37",
      "sourceName": "@openzeppelin/contracts/token/ERC20/IERC20.sol",
      "solcConfig": {
        "version": "0.8.10",
        "settings": {
          "optimizer": {
            "enabled": false,
            "runs": 200
          },
          "outputSelection": {
            "*": {
              "*": [
                "abi",
                "evm.bytecode",
                "evm.deployedBytecode",
                "evm.methodIdentifiers",
                "metadata"
              ],
              "": [
                "ast"
              ]
            }
          }
        }
      },
      "imports": [],
      "versionPragmas": [
        "^0.8.0"
      ],
      "artifacts": [
        "IERC20"
      ]
    },
    "/mnt/user-data/joe/aztec-connect-bridges/src/bridges/example/ExampleBridge.sol": {
      "lastModificationDate": 1644078770742,
      "contentHash": "481f163d587bc864bc2f790657d7aca2",
      "sourceName": "src/bridges/example/ExampleBridge.sol",
      "solcConfig": {
        "version": "0.8.10",
        "settings": {
          "optimizer": {
            "enabled": false,
            "runs": 200
          },
          "outputSelection": {
            "*": {
              "*": [
                "abi",
                "evm.bytecode",
                "evm.deployedBytecode",
                "evm.methodIdentifiers",
                "metadata"
              ],
              "": [
                "ast"
              ]
            }
          }
        }
      },
      "imports": [
        "@openzeppelin/contracts/utils/math/SafeMath.sol",
        "../../interfaces/IDefiBridge.sol",
        "@openzeppelin/contracts/token/ERC20/IERC20.sol",
        "../../aztec/AztecTypes.sol"
      ],
      "versionPragmas": [
        ">=0.6.10 <=0.8.10"
      ],
      "artifacts": [
        "ExampleBridgeContract"
      ]
    },
    "/mnt/user-data/joe/aztec-connect-bridges/lib/ds-test/src/test.sol": {
      "lastModificationDate": 1644078493524,
      "contentHash": "5d45a46528eaf8a26f0a8d93669f3148",
      "sourceName": "lib/ds-test/src/test.sol",
      "solcConfig": {
        "version": "0.8.10",
        "settings": {
          "optimizer": {
            "enabled": false,
            "runs": 200
          },
          "outputSelection": {
            "*": {
              "*": [
                "abi",
                "evm.bytecode",
                "evm.deployedBytecode",
                "evm.methodIdentifiers",
                "metadata"
              ],
              "": [
                "ast"
              ]
            }
          }
        }
      },
      "imports": [],
      "versionPragmas": [
        ">=0.4.23"
      ],
      "artifacts": [
        "DSTest"
      ]
    },
    "/mnt/user-data/joe/aztec-connect-bridges/node_modules/@openzeppelin/contracts/utils/math/SafeMath.sol": {
      "lastModificationDate": 1644078429920,
      "contentHash": "a6a9d6c1f662e922b82c1ba4d81cdd48",
      "sourceName": "@openzeppelin/contracts/utils/math/SafeMath.sol",
      "solcConfig": {
        "version": "0.8.10",
        "settings": {
          "optimizer": {
            "enabled": false,
            "runs": 200
          },
          "outputSelection": {
            "*": {
              "*": [
                "abi",
                "evm.bytecode",
                "evm.deployedBytecode",
                "evm.methodIdentifiers",
                "metadata"
              ],
              "": [
                "ast"
              ]
            }
          }
        }
      },
      "imports": [],
      "versionPragmas": [
        "^0.8.0"
      ],
      "artifacts": [
        "SafeMath"
      ]
    },
    "/mnt/user-data/joe/aztec-connect-bridges/src/interfaces/IDefiBridge.sol": {
      "lastModificationDate": 1644078770742,
      "contentHash": "178d9abb37ffbc4319ce56fe46b421b2",
      "sourceName": "src/interfaces/IDefiBridge.sol",
      "solcConfig": {
        "version": "0.8.10",
        "settings": {
          "optimizer": {
            "enabled": false,
            "runs": 200
          },
          "outputSelection": {
            "*": {
              "*": [
                "abi",
                "evm.bytecode",
                "evm.deployedBytecode",
                "evm.methodIdentifiers",
                "metadata"
              ],
              "": [
                "ast"
              ]
            }
          }
        }
      },
      "imports": [
        "../aztec/AztecTypes.sol"
      ],
      "versionPragmas": [
        ">=0.6.6 <0.8.11"
      ],
      "artifacts": [
        "IDefiBridge"
      ]
    },
    "/mnt/user-data/joe/aztec-connect-bridges/src/libraries/TokenTransfers.sol": {
      "lastModificationDate": 1644078770742,
      "contentHash": "0dd65104d9c1009c49cfff15081a0600",
      "sourceName": "src/libraries/TokenTransfers.sol",
      "solcConfig": {
        "version": "0.8.10",
        "settings": {
          "optimizer": {
            "enabled": false,
            "runs": 200
          },
          "outputSelection": {
            "*": {
              "*": [
                "abi",
                "evm.bytecode",
                "evm.deployedBytecode",
                "evm.methodIdentifiers",
                "metadata"
              ],
              "": [
                "ast"
              ]
            }
          }
        }
      },
      "imports": [],
      "versionPragmas": [
        ">=0.8.4 <0.8.11"
      ],
      "artifacts": [
        "TokenTransfers"
      ]
    },
    "/mnt/user-data/joe/aztec-connect-bridges/src/interfaces/IERC20Permit.sol": {
      "lastModificationDate": 1644078770742,
      "contentHash": "2f171100ea310c7c552990878cfec17f",
      "sourceName": "src/interfaces/IERC20Permit.sol",
      "solcConfig": {
        "version": "0.8.10",
        "settings": {
          "optimizer": {
            "enabled": false,
            "runs": 200
          },
          "outputSelection": {
            "*": {
              "*": [
                "abi",
                "evm.bytecode",
                "evm.deployedBytecode",
                "evm.methodIdentifiers",
                "metadata"
              ],
              "": [
                "ast"
              ]
            }
          }
        }
      },
      "imports": [
        "@openzeppelin/contracts/token/ERC20/IERC20.sol"
      ],
      "versionPragmas": [
        ">=0.6.10 <=0.8.10"
      ],
      "artifacts": [
        "IERC20Permit"
      ]
    },
    "/mnt/user-data/joe/aztec-connect-bridges/src/test/element/Element.t.sol": {
      "lastModificationDate": 1644321379410,
      "contentHash": "23e4930a029c0c614802e1bf42ad8315",
      "sourceName": "src/test/element/Element.t.sol",
      "solcConfig": {
        "version": "0.8.10",
        "settings": {
          "optimizer": {
            "enabled": false,
            "runs": 200
          },
          "outputSelection": {
            "*": {
              "*": [
                "abi",
                "evm.bytecode",
                "evm.deployedBytecode",
                "evm.methodIdentifiers",
                "metadata"
              ],
              "": [
                "ast"
              ]
            }
          }
        }
      },
      "imports": [
        "../Vm.sol",
        "./../../aztec/DefiBridgeProxy.sol",
        "./../../aztec/RollupProcessor.sol",
        "@openzeppelin/contracts/token/ERC20/IERC20.sol",
        "./../../bridges/element/ElementBridge.sol",
        "./../../aztec/AztecTypes.sol",
        "../../../lib/ds-test/src/test.sol"
      ],
      "versionPragmas": [
        "0.8.10"
      ],
      "artifacts": [
        "ElementTest"
      ]
    },
    "/mnt/user-data/joe/aztec-connect-bridges/src/bridges/element/ElementBridge.sol": {
      "lastModificationDate": 1644320576228,
      "contentHash": "25f422c6f3710da715939b69e42c8cc4",
      "sourceName": "src/bridges/element/ElementBridge.sol",
      "solcConfig": {
        "version": "0.8.10",
        "settings": {
          "optimizer": {
            "enabled": false,
            "runs": 200
          },
          "outputSelection": {
            "*": {
              "*": [
                "abi",
                "evm.bytecode",
                "evm.deployedBytecode",
                "evm.methodIdentifiers",
                "metadata"
              ],
              "": [
                "ast"
              ]
            }
          }
        }
      },
      "imports": [
        "@openzeppelin/contracts/utils/math/SafeMath.sol",
        "@openzeppelin/contracts/token/ERC20/ERC20.sol",
        "./interfaces/IVault.sol",
        "./interfaces/IPool.sol",
        "./interfaces/ITranche.sol",
        "./interfaces/IERC20Permit.sol",
        "./interfaces/IWrappedPosition.sol",
        "./interfaces/IRollupProcessor.sol",
        "../../interfaces/IDefiBridge.sol",
        "../../aztec/AztecTypes.sol",
        "../../test/console.sol"
      ],
      "versionPragmas": [
        ">=0.6.10 <=0.8.10"
      ],
      "artifacts": [
        "ElementBridge"
      ]
    },
    "/mnt/user-data/joe/aztec-connect-bridges/node_modules/@openzeppelin/contracts/token/ERC20/ERC20.sol": {
      "lastModificationDate": 1644078429920,
      "contentHash": "f48de0eaae9544072b8766e2eac528a7",
      "sourceName": "@openzeppelin/contracts/token/ERC20/ERC20.sol",
      "solcConfig": {
        "version": "0.8.10",
        "settings": {
          "optimizer": {
            "enabled": false,
            "runs": 200
          },
          "outputSelection": {
            "*": {
              "*": [
                "abi",
                "evm.bytecode",
                "evm.deployedBytecode",
                "evm.methodIdentifiers",
                "metadata"
              ],
              "": [
                "ast"
              ]
            }
          }
        }
      },
      "imports": [
        "./IERC20.sol",
        "./extensions/IERC20Metadata.sol",
        "../../utils/Context.sol"
      ],
      "versionPragmas": [
        "^0.8.0"
      ],
      "artifacts": [
        "ERC20"
      ]
    },
    "/mnt/user-data/joe/aztec-connect-bridges/src/bridges/element/interfaces/IVault.sol": {
      "lastModificationDate": 1644078770742,
      "contentHash": "53d7ce15ed9a64e56bfa662a6d2e6df7",
      "sourceName": "src/bridges/element/interfaces/IVault.sol",
      "solcConfig": {
        "version": "0.8.10",
        "settings": {
          "optimizer": {
            "enabled": false,
            "runs": 200
          },
          "outputSelection": {
            "*": {
              "*": [
                "abi",
                "evm.bytecode",
                "evm.deployedBytecode",
                "evm.methodIdentifiers",
                "metadata"
              ],
              "": [
                "ast"
              ]
            }
          }
        }
      },
      "imports": [],
      "versionPragmas": [
        "<=0.8.10"
      ],
      "artifacts": [
        "IAsset",
        "IVault"
      ]
    },
    "/mnt/user-data/joe/aztec-connect-bridges/src/bridges/element/interfaces/IPool.sol": {
      "lastModificationDate": 1644078770742,
      "contentHash": "84521f7f69df2c04f05c4fa78160d094",
      "sourceName": "src/bridges/element/interfaces/IPool.sol",
      "solcConfig": {
        "version": "0.8.10",
        "settings": {
          "optimizer": {
            "enabled": false,
            "runs": 200
          },
          "outputSelection": {
            "*": {
              "*": [
                "abi",
                "evm.bytecode",
                "evm.deployedBytecode",
                "evm.methodIdentifiers",
                "metadata"
              ],
              "": [
                "ast"
              ]
            }
          }
        }
      },
      "imports": [
        "./IERC20Permit.sol",
        "./IVault.sol"
      ],
      "versionPragmas": [
        ">=0.7.5"
      ],
      "artifacts": [
        "IPool"
      ]
    },
    "/mnt/user-data/joe/aztec-connect-bridges/src/bridges/element/interfaces/ITranche.sol": {
      "lastModificationDate": 1644078770742,
      "contentHash": "346e799c3e92c5d80894bdd9298cb23a",
      "sourceName": "src/bridges/element/interfaces/ITranche.sol",
      "solcConfig": {
        "version": "0.8.10",
        "settings": {
          "optimizer": {
            "enabled": false,
            "runs": 200
          },
          "outputSelection": {
            "*": {
              "*": [
                "abi",
                "evm.bytecode",
                "evm.deployedBytecode",
                "evm.methodIdentifiers",
                "metadata"
              ],
              "": [
                "ast"
              ]
            }
          }
        }
      },
      "imports": [
        "./IERC20Permit.sol"
      ],
      "versionPragmas": [
        ">=0.6.10 <=0.8.10"
      ],
      "artifacts": [
        "ITranche"
      ]
    },
    "/mnt/user-data/joe/aztec-connect-bridges/src/bridges/element/interfaces/IERC20Permit.sol": {
      "lastModificationDate": 1644078770742,
      "contentHash": "2f171100ea310c7c552990878cfec17f",
      "sourceName": "src/bridges/element/interfaces/IERC20Permit.sol",
      "solcConfig": {
        "version": "0.8.10",
        "settings": {
          "optimizer": {
            "enabled": false,
            "runs": 200
          },
          "outputSelection": {
            "*": {
              "*": [
                "abi",
                "evm.bytecode",
                "evm.deployedBytecode",
                "evm.methodIdentifiers",
                "metadata"
              ],
              "": [
                "ast"
              ]
            }
          }
        }
      },
      "imports": [
        "@openzeppelin/contracts/token/ERC20/IERC20.sol"
      ],
      "versionPragmas": [
        ">=0.6.10 <=0.8.10"
      ],
      "artifacts": [
        "IERC20Permit"
      ]
    },
    "/mnt/user-data/joe/aztec-connect-bridges/src/bridges/element/interfaces/IWrappedPosition.sol": {
      "lastModificationDate": 1644078770742,
      "contentHash": "2a1abf592e67f5852b6c022811885592",
      "sourceName": "src/bridges/element/interfaces/IWrappedPosition.sol",
      "solcConfig": {
        "version": "0.8.10",
        "settings": {
          "optimizer": {
            "enabled": false,
            "runs": 200
          },
          "outputSelection": {
            "*": {
              "*": [
                "abi",
                "evm.bytecode",
                "evm.deployedBytecode",
                "evm.methodIdentifiers",
                "metadata"
              ],
              "": [
                "ast"
              ]
            }
          }
        }
      },
      "imports": [
        "./IERC20Permit.sol"
      ],
      "versionPragmas": [
        "^0.8.0"
      ],
      "artifacts": [
        "IWrappedPosition"
      ]
    },
    "/mnt/user-data/joe/aztec-connect-bridges/src/bridges/element/interfaces/IRollupProcessor.sol": {
      "lastModificationDate": 1644078770742,
      "contentHash": "f335dbbb24ac52b82b8be52e46d2a6b1",
      "sourceName": "src/bridges/element/interfaces/IRollupProcessor.sol",
      "solcConfig": {
        "version": "0.8.10",
        "settings": {
          "optimizer": {
            "enabled": false,
            "runs": 200
          },
          "outputSelection": {
            "*": {
              "*": [
                "abi",
                "evm.bytecode",
                "evm.deployedBytecode",
                "evm.methodIdentifiers",
                "metadata"
              ],
              "": [
                "ast"
              ]
            }
          }
        }
      },
      "imports": [],
      "versionPragmas": [
        ">=0.6.10 <=0.8.10"
      ],
      "artifacts": [
        "IRollupProcessor"
      ]
    },
    "/mnt/user-data/joe/aztec-connect-bridges/src/test/console.sol": {
      "lastModificationDate": 1644078770742,
      "contentHash": "907ccc8c5df3f256f3e4c4a215f521a1",
      "sourceName": "src/test/console.sol",
      "solcConfig": {
        "version": "0.8.10",
        "settings": {
          "optimizer": {
            "enabled": false,
            "runs": 200
          },
          "outputSelection": {
            "*": {
              "*": [
                "abi",
                "evm.bytecode",
                "evm.deployedBytecode",
                "evm.methodIdentifiers",
                "metadata"
              ],
              "": [
                "ast"
              ]
            }
          }
        }
      },
      "imports": [],
      "versionPragmas": [
        ">=0.4.22 <0.9.0"
      ],
      "artifacts": [
        "console"
      ]
    },
    "/mnt/user-data/joe/aztec-connect-bridges/node_modules/@openzeppelin/contracts/token/ERC20/extensions/IERC20Metadata.sol": {
      "lastModificationDate": 1644078430156,
      "contentHash": "909ab67fc5c25033fe6cd364f8c056f9",
      "sourceName": "@openzeppelin/contracts/token/ERC20/extensions/IERC20Metadata.sol",
      "solcConfig": {
        "version": "0.8.10",
        "settings": {
          "optimizer": {
            "enabled": false,
            "runs": 200
          },
          "outputSelection": {
            "*": {
              "*": [
                "abi",
                "evm.bytecode",
                "evm.deployedBytecode",
                "evm.methodIdentifiers",
                "metadata"
              ],
              "": [
                "ast"
              ]
            }
          }
        }
      },
      "imports": [
        "../IERC20.sol"
      ],
      "versionPragmas": [
        "^0.8.0"
      ],
      "artifacts": [
        "IERC20Metadata"
      ]
    },
    "/mnt/user-data/joe/aztec-connect-bridges/node_modules/@openzeppelin/contracts/utils/Context.sol": {
      "lastModificationDate": 1644078429396,
      "contentHash": "5f2c5c4b6af2dd4551027144797bc8be",
      "sourceName": "@openzeppelin/contracts/utils/Context.sol",
      "solcConfig": {
        "version": "0.8.10",
        "settings": {
          "optimizer": {
            "enabled": false,
            "runs": 200
          },
          "outputSelection": {
            "*": {
              "*": [
                "abi",
                "evm.bytecode",
                "evm.deployedBytecode",
                "evm.methodIdentifiers",
                "metadata"
              ],
              "": [
                "ast"
              ]
            }
          }
        }
      },
      "imports": [],
      "versionPragmas": [
        "^0.8.0"
      ],
      "artifacts": [
        "Context"
      ]
    },
    "/mnt/user-data/joe/aztec-connect-bridges/src/test/aave/Aave.t.sol": {
      "lastModificationDate": 1644321375258,
      "contentHash": "6bb5aa5b043c732f7d71d6b18be24bd8",
      "sourceName": "src/test/aave/Aave.t.sol",
      "solcConfig": {
        "version": "0.8.10",
        "settings": {
          "optimizer": {
            "enabled": false,
            "runs": 200
          },
          "outputSelection": {
            "*": {
              "*": [
                "abi",
                "evm.bytecode",
                "evm.deployedBytecode",
                "evm.methodIdentifiers",
                "metadata"
              ],
              "": [
                "ast"
              ]
            }
          }
        }
      },
      "imports": [
        "../Vm.sol",
        "./../../aztec/DefiBridgeProxy.sol",
        "./../../aztec/RollupProcessor.sol",
        "@openzeppelin/contracts/token/ERC20/IERC20.sol",
        "./../../bridges/aave/AaveLending.sol",
        "./../../bridges/aave/interfaces/IPool.sol",
        "./../../bridges/aave/interfaces/ILendingPoolAddressesProvider.sol",
        "./../../bridges/aave/interfaces/IAToken.sol",
        "./../../bridges/aave/ZkAToken.sol",
        "./../../aztec/AztecTypes.sol",
        "./../../bridges/aave/libraries/WadRayMath.sol",
        "../../../lib/ds-test/src/test.sol"
      ],
      "versionPragmas": [
        "0.8.10"
      ],
      "artifacts": [
        "AaveTest"
      ]
    },
    "/mnt/user-data/joe/aztec-connect-bridges/src/bridges/aave/AaveLending.sol": {
      "lastModificationDate": 1644078770742,
      "contentHash": "2b1acbc67302df6e66329afa9e3bb411",
      "sourceName": "src/bridges/aave/AaveLending.sol",
      "solcConfig": {
        "version": "0.8.10",
        "settings": {
          "optimizer": {
            "enabled": false,
            "runs": 200
          },
          "outputSelection": {
            "*": {
              "*": [
                "abi",
                "evm.bytecode",
                "evm.deployedBytecode",
                "evm.methodIdentifiers",
                "metadata"
              ],
              "": [
                "ast"
              ]
            }
          }
        }
      },
      "imports": [
        "@openzeppelin/contracts/utils/math/SafeMath.sol",
        "../../interfaces/IDefiBridge.sol",
        "./interfaces/ILendingPoolAddressesProvider.sol",
        "./interfaces/IERC20.sol",
        "./interfaces/IPool.sol",
        "./interfaces/IScaledBalanceToken.sol",
        "../../aztec/AztecTypes.sol",
        "./ZkAToken.sol",
        "./libraries/WadRayMath.sol",
        "./DataTypes.sol"
      ],
      "versionPragmas": [
        ">=0.6.10 <=0.8.10"
      ],
      "artifacts": [
        "AaveLendingBridge"
      ]
    },
    "/mnt/user-data/joe/aztec-connect-bridges/src/bridges/aave/interfaces/IPool.sol": {
      "lastModificationDate": 1644078770742,
      "contentHash": "878e68c87bba2c16868105ddb8218477",
      "sourceName": "src/bridges/aave/interfaces/IPool.sol",
      "solcConfig": {
        "version": "0.8.10",
        "settings": {
          "optimizer": {
            "enabled": false,
            "runs": 200
          },
          "outputSelection": {
            "*": {
              "*": [
                "abi",
                "evm.bytecode",
                "evm.deployedBytecode",
                "evm.methodIdentifiers",
                "metadata"
              ],
              "": [
                "ast"
              ]
            }
          }
        }
      },
      "imports": [
        "./../DataTypes.sol"
      ],
      "versionPragmas": [
        ">=0.6.10 <=0.8.10"
      ],
      "artifacts": [
        "IPool"
      ]
    },
    "/mnt/user-data/joe/aztec-connect-bridges/src/bridges/aave/interfaces/ILendingPoolAddressesProvider.sol": {
      "lastModificationDate": 1644078770742,
      "contentHash": "b87dd49ce4603f9d32ab828e48ff085e",
      "sourceName": "src/bridges/aave/interfaces/ILendingPoolAddressesProvider.sol",
      "solcConfig": {
        "version": "0.8.10",
        "settings": {
          "optimizer": {
            "enabled": false,
            "runs": 200
          },
          "outputSelection": {
            "*": {
              "*": [
                "abi",
                "evm.bytecode",
                "evm.deployedBytecode",
                "evm.methodIdentifiers",
                "metadata"
              ],
              "": [
                "ast"
              ]
            }
          }
        }
      },
      "imports": [],
      "versionPragmas": [
        ">=0.6.10 <=0.8.10"
      ],
      "artifacts": [
        "ILendingPoolAddressesProvider"
      ]
    },
    "/mnt/user-data/joe/aztec-connect-bridges/src/bridges/aave/interfaces/IAToken.sol": {
      "lastModificationDate": 1644078770742,
      "contentHash": "f8f4f95dd41d25a2c172f821abefbc6a",
      "sourceName": "src/bridges/aave/interfaces/IAToken.sol",
      "solcConfig": {
        "version": "0.8.10",
        "settings": {
          "optimizer": {
            "enabled": false,
            "runs": 200
          },
          "outputSelection": {
            "*": {
              "*": [
                "abi",
                "evm.bytecode",
                "evm.deployedBytecode",
                "evm.methodIdentifiers",
                "metadata"
              ],
              "": [
                "ast"
              ]
            }
          }
        }
      },
      "imports": [
        "./IERC20.sol"
      ],
      "versionPragmas": [
        ">=0.6.10 <=0.8.10"
      ],
      "artifacts": [
        "IAToken"
      ]
    },
    "/mnt/user-data/joe/aztec-connect-bridges/src/bridges/aave/ZkAToken.sol": {
      "lastModificationDate": 1644078770742,
      "contentHash": "cddc3a1b070006544174f02e09f45c3a",
      "sourceName": "src/bridges/aave/ZkAToken.sol",
      "solcConfig": {
        "version": "0.8.10",
        "settings": {
          "optimizer": {
            "enabled": false,
            "runs": 200
          },
          "outputSelection": {
            "*": {
              "*": [
                "abi",
                "evm.bytecode",
                "evm.deployedBytecode",
                "evm.methodIdentifiers",
                "metadata"
              ],
              "": [
                "ast"
              ]
            }
          }
        }
      },
      "imports": [
        "@openzeppelin/contracts/token/ERC20/extensions/ERC20Burnable.sol",
        "@openzeppelin/contracts/token/ERC20/ERC20.sol"
      ],
      "versionPragmas": [
        ">=0.6.10 <=0.8.10"
      ],
      "artifacts": [
        "IZkAToken",
        "ZkAToken"
      ]
    },
    "/mnt/user-data/joe/aztec-connect-bridges/src/bridges/aave/libraries/WadRayMath.sol": {
      "lastModificationDate": 1644078770742,
      "contentHash": "5a1897eec542152688a15b14464aef0e",
      "sourceName": "src/bridges/aave/libraries/WadRayMath.sol",
      "solcConfig": {
        "version": "0.8.10",
        "settings": {
          "optimizer": {
            "enabled": false,
            "runs": 200
          },
          "outputSelection": {
            "*": {
              "*": [
                "abi",
                "evm.bytecode",
                "evm.deployedBytecode",
                "evm.methodIdentifiers",
                "metadata"
              ],
              "": [
                "ast"
              ]
            }
          }
        }
      },
      "imports": [],
      "versionPragmas": [
        ">=0.6.10 <=0.8.10"
      ],
      "artifacts": [
        "WadRayMath"
      ]
    },
    "/mnt/user-data/joe/aztec-connect-bridges/src/bridges/aave/interfaces/IERC20.sol": {
      "lastModificationDate": 1644078770742,
      "contentHash": "8dd377d14e85a7e88b981d0511fbf11a",
      "sourceName": "src/bridges/aave/interfaces/IERC20.sol",
      "solcConfig": {
        "version": "0.8.10",
        "settings": {
          "optimizer": {
            "enabled": false,
            "runs": 200
          },
          "outputSelection": {
            "*": {
              "*": [
                "abi",
                "evm.bytecode",
                "evm.deployedBytecode",
                "evm.methodIdentifiers",
                "metadata"
              ],
              "": [
                "ast"
              ]
            }
          }
        }
      },
      "imports": [],
      "versionPragmas": [
        ">=0.6.10 <=0.8.10"
      ],
      "artifacts": [
        "IERC20",
        "IERC20Detailed"
      ]
    },
    "/mnt/user-data/joe/aztec-connect-bridges/src/bridges/aave/interfaces/IScaledBalanceToken.sol": {
      "lastModificationDate": 1644078770742,
      "contentHash": "707f40eb3bf63cf5a46a055f96373ab2",
      "sourceName": "src/bridges/aave/interfaces/IScaledBalanceToken.sol",
      "solcConfig": {
        "version": "0.8.10",
        "settings": {
          "optimizer": {
            "enabled": false,
            "runs": 200
          },
          "outputSelection": {
            "*": {
              "*": [
                "abi",
                "evm.bytecode",
                "evm.deployedBytecode",
                "evm.methodIdentifiers",
                "metadata"
              ],
              "": [
                "ast"
              ]
            }
          }
        }
      },
      "imports": [],
      "versionPragmas": [
        ">=0.6.10 <=0.8.10"
      ],
      "artifacts": [
        "IScaledBalanceToken"
      ]
    },
    "/mnt/user-data/joe/aztec-connect-bridges/src/bridges/aave/DataTypes.sol": {
      "lastModificationDate": 1644078770742,
      "contentHash": "0503dd7ca17f76371fa5fc5150c0714d",
      "sourceName": "src/bridges/aave/DataTypes.sol",
      "solcConfig": {
        "version": "0.8.10",
        "settings": {
          "optimizer": {
            "enabled": false,
            "runs": 200
          },
          "outputSelection": {
            "*": {
              "*": [
                "abi",
                "evm.bytecode",
                "evm.deployedBytecode",
                "evm.methodIdentifiers",
                "metadata"
              ],
              "": [
                "ast"
              ]
            }
          }
        }
      },
      "imports": [],
      "versionPragmas": [
        ">=0.6.10 <=0.8.10"
      ],
      "artifacts": [
        "DataTypes"
      ]
    },
    "/mnt/user-data/joe/aztec-connect-bridges/node_modules/@openzeppelin/contracts/token/ERC20/extensions/ERC20Burnable.sol": {
      "lastModificationDate": 1644078430156,
      "contentHash": "9f43a2bc39b89ae302f1727697f9c420",
      "sourceName": "@openzeppelin/contracts/token/ERC20/extensions/ERC20Burnable.sol",
      "solcConfig": {
        "version": "0.8.10",
        "settings": {
          "optimizer": {
            "enabled": false,
            "runs": 200
          },
          "outputSelection": {
            "*": {
              "*": [
                "abi",
                "evm.bytecode",
                "evm.deployedBytecode",
                "evm.methodIdentifiers",
                "metadata"
              ],
              "": [
                "ast"
              ]
            }
          }
        }
      },
      "imports": [
        "../ERC20.sol",
        "../../../utils/Context.sol"
      ],
      "versionPragmas": [
        "^0.8.0"
      ],
      "artifacts": [
        "ERC20Burnable"
      ]
    },
    "/mnt/user-data/joe/aztec-connect-bridges/src/test/aave/Rounding.sol": {
      "lastModificationDate": 1644321372290,
      "contentHash": "2e004857c08ab94ffa775371b8537888",
      "sourceName": "src/test/aave/Rounding.sol",
      "solcConfig": {
        "version": "0.8.10",
        "settings": {
          "optimizer": {
            "enabled": false,
            "runs": 200
          },
          "outputSelection": {
            "*": {
              "*": [
                "abi",
                "evm.bytecode",
                "evm.deployedBytecode",
                "evm.methodIdentifiers",
                "metadata"
              ],
              "": [
                "ast"
              ]
            }
          }
        }
      },
      "imports": [
        "../../../lib/ds-test/src/test.sol",
        "./../../bridges/aave/libraries/WadRayMath.sol"
      ],
      "versionPragmas": [
        "0.8.10"
      ],
      "artifacts": [
        "RoundingTest"
      ]
    },
    "/mnt/user-data/joe/aztec-connect-bridges/src/aztec/ERC20Mintable.sol": {
      "lastModificationDate": 1644078770742,
      "contentHash": "6b527f9970827b68686307d8a3a67a5b",
      "sourceName": "src/aztec/ERC20Mintable.sol",
      "solcConfig": {
        "version": "0.8.10",
        "settings": {
          "optimizer": {
            "enabled": false,
            "runs": 200
          },
          "outputSelection": {
            "*": {
              "*": [
                "abi",
                "evm.bytecode",
                "evm.deployedBytecode",
                "evm.methodIdentifiers",
                "metadata"
              ],
              "": [
                "ast"
              ]
            }
          }
        }
      },
      "imports": [
        "@openzeppelin/contracts/token/ERC20/ERC20.sol"
      ],
      "versionPragmas": [
        ">=0.6.10 <=0.8.10"
      ],
      "artifacts": [
        "ERC20Mintable"
      ]
    },
    "/mnt/user-data/joe/aztec-connect-bridges/src/interfaces/IRollupProcessor.sol": {
      "lastModificationDate": 1644331401725,
      "contentHash": "06c02d6bf93e7eeea38080e61446c185",
      "sourceName": "src/interfaces/IRollupProcessor.sol",
      "solcConfig": {
        "version": "0.8.10",
        "settings": {
          "optimizer": {
            "enabled": false,
            "runs": 200
          },
          "outputSelection": {
            "*": {
              "*": [
                "abi",
                "evm.bytecode",
                "evm.deployedBytecode",
                "evm.methodIdentifiers",
                "metadata"
              ],
              "": [
                "ast"
              ]
            }
          }
        }
      },
      "imports": [],
      "versionPragmas": [
        ">=0.8.4 <0.8.11"
      ],
      "artifacts": [
        "IRollupProcessor"
      ]
    },
    "/mnt/user-data/joe/aztec-connect-bridges/src/interfaces/IWETH.sol": {
      "lastModificationDate": 1644078770742,
      "contentHash": "f869ff1a3d19edb6970c3291481453f2",
      "sourceName": "src/interfaces/IWETH.sol",
      "solcConfig": {
        "version": "0.8.10",
        "settings": {
          "optimizer": {
            "enabled": false,
            "runs": 200
          },
          "outputSelection": {
            "*": {
              "*": [
                "abi",
                "evm.bytecode",
                "evm.deployedBytecode",
                "evm.methodIdentifiers",
                "metadata"
              ],
              "": [
                "ast"
              ]
            }
          }
        }
      },
      "imports": [],
      "versionPragmas": [
        ">=0.7.5"
      ],
      "artifacts": [
        "WETH"
      ]
    }
  }
}
